plottergeist/VERSION.txt
plottergeist/__init__.py
plottergeist/fig_creator.py
plottergeist/histogram.py
plottergeist/new_histogram.py
plottergeist/residuals.py
plottergeist/style.py
plottergeist/test.py
plottergeist/test_histogram.py
plottergeist-0.10.0.dist-info/LICENSE
plottergeist-0.10.0.dist-info/METADATA
plottergeist-0.10.0.dist-info/WHEEL
plottergeist-0.10.0.dist-info/top_level.txt
plottergeist-0.10.0.dist-info/RECORD
